gcp_toolkit/__init__.py
gcp_toolkit/scheduler.py
gcp_toolkit/storage.py
gcp_toolkit-0.1.0.dist-info/LICENSE
gcp_toolkit-0.1.0.dist-info/METADATA
gcp_toolkit-0.1.0.dist-info/WHEEL
gcp_toolkit-0.1.0.dist-info/top_level.txt
gcp_toolkit-0.1.0.dist-info/RECORD
