Metadata-Version: 2.1
Name: gcp_toolkit
Version: 0.1.0
Summary: Utilities for interacting with GCP Storage and Scheduler
Author-email: Atoosa Nasiri <atoosa.nasiri@gmail.com>
License: MIT
Requires-Python: >=3.8
License-File: LICENSE
Requires-Dist: google-cloud-storage
Requires-Dist: google-cloud-scheduler
Requires-Dist: protobuf
